difr/__init__.py
difr/feature_extractor.py
difr/main.py
difr/models/feature_extractor.onnx
difr/similar_image_finder.py
difr-1.0.2.dist-info/LICENSE
difr-1.0.2.dist-info/METADATA
difr-1.0.2.dist-info/WHEEL
difr-1.0.2.dist-info/entry_points.txt
difr-1.0.2.dist-info/RECORD
