Metadata-Version: 2.1
Name: difr
Version: 1.0.2
Summary: This tool offers a solution for identifying and managing similar images across multiple directories.
Home-page: https://github.com/opqrstuvcut/
Author: opqrstuvcut
Requires-Python: >=3.9,<4.0
Classifier: Programming Language :: Python :: 3
Classifier: Programming Language :: Python :: 3.9
Classifier: Programming Language :: Python :: 3.10
Classifier: Programming Language :: Python :: 3.11
Classifier: Programming Language :: Python :: 3.12
Requires-Dist: Pillow (>=10.0.0,<11.0.0)
Requires-Dist: onnxruntime (>=1.10,<2.0)
Requires-Dist: rich (>=13.0.0,<14.0.0)
Project-URL: Repository, https://github.com/opqrstuvcut/DIFR
